{"skeleton":{"hash":"+A+AeRj6LeliijB23d/QYUhLAnE","spine":"3.8.99","images":"./images/","audio":"G:/20201010界面/spine动画源文件/人物动画/150+角色spine/spineaaa"},"bones":[{"name":"root"},{"name":"all","parent":"root"},{"name":"hit","parent":"all"},{"name":"zidan","parent":"all","rotation":90,"x":-97.63}],"slots":[{"name":"hit","bone":"hit"},{"name":"zidan","bone":"zidan"}],"skins":[{"name":"default","attachments":{"hit":{"heilongpugong/hit/shouji_00019":{"y":0.5,"width":256,"height":237},"heilongpugong/hit/shouji_00020":{"y":0.5,"width":256,"height":237},"heilongpugong/hit/shouji_00021":{"y":0.5,"width":256,"height":237},"heilongpugong/hit/shouji_00022":{"y":0.5,"width":256,"height":237},"heilongpugong/hit/shouji_00023":{"y":0.5,"width":256,"height":237},"heilongpugong/hit/shouji_00024":{"y":0.5,"width":256,"height":237},"heilongpugong/hit/shouji_00025":{"y":0.5,"width":256,"height":237},"heilongpugong/hit/shouji_00026":{"y":0.5,"width":256,"height":237},"heilongpugong/hit/shouji_00027":{"y":0.5,"width":256,"height":237},"heilongpugong/hit/shouji_00028":{"y":0.5,"width":256,"height":237},"heilongpugong/hit/shouji_00029":{"y":0.5,"width":256,"height":237},"heilongpugong/hit/shouji_00030":{"y":0.5,"width":256,"height":237},"heilongpugong/hit/shouji_00031":{"y":0.5,"width":256,"height":237},"heilongpugong/hit/shouji_00032":{"y":0.5,"width":256,"height":237},"heilongpugong/hit/shouji_00033":{"y":0.5,"width":256,"height":237},"heilongpugong/hit/shouji_00034":{"y":0.5,"width":256,"height":237}},"zidan":{"heilongpugong/zidan/huoqiu_00000":{"x":0.5,"y":0.5,"width":115,"height":277},"heilongpugong/zidan/huoqiu_00001":{"x":0.5,"y":0.5,"width":115,"height":277},"heilongpugong/zidan/huoqiu_00002":{"x":0.5,"y":0.5,"width":115,"height":277},"heilongpugong/zidan/huoqiu_00003":{"x":0.5,"y":0.5,"width":115,"height":277},"heilongpugong/zidan/huoqiu_00004":{"x":0.5,"y":0.5,"width":115,"height":277},"heilongpugong/zidan/huoqiu_00005":{"x":0.5,"y":0.5,"width":115,"height":277},"heilongpugong/zidan/huoqiu_00006":{"x":0.5,"y":0.5,"width":115,"height":277},"heilongpugong/zidan/huoqiu_00007":{"x":0.5,"y":0.5,"width":115,"height":277},"heilongpugong/zidan/huoqiu_00008":{"x":0.5,"y":0.5,"width":115,"height":277},"heilongpugong/zidan/huoqiu_00009":{"x":0.5,"y":0.5,"width":115,"height":277},"heilongpugong/zidan/huoqiu_00010":{"x":0.5,"y":0.5,"width":115,"height":277},"heilongpugong/zidan/huoqiu_00011":{"x":0.5,"y":0.5,"width":115,"height":277},"heilongpugong/zidan/huoqiu_00012":{"x":0.5,"y":0.5,"width":115,"height":277},"heilongpugong/zidan/huoqiu_00013":{"x":0.5,"y":0.5,"width":115,"height":277},"heilongpugong/zidan/huoqiu_00014":{"x":0.5,"y":0.5,"width":115,"height":277},"heilongpugong/zidan/huoqiu_00015":{"x":0.5,"y":0.5,"width":115,"height":277},"heilongpugong/zidan/huoqiu_00016":{"x":0.5,"y":0.5,"width":115,"height":277},"heilongpugong/zidan/huoqiu_00017":{"x":0.5,"y":0.5,"width":115,"height":277},"heilongpugong/zidan/huoqiu_00018":{"x":0.5,"y":0.5,"width":115,"height":277},"heilongpugong/zidan/huoqiu_00019":{"x":0.5,"y":0.5,"width":115,"height":277},"heilongpugong/zidan/huoqiu_00020":{"x":0.5,"y":0.5,"width":115,"height":277},"heilongpugong/zidan/huoqiu_00021":{"x":0.5,"y":0.5,"width":115,"height":277}}}}],"animations":{"general_tail":{"slots":{"zidan":{"attachment":[{"name":"heilongpugong/zidan/huoqiu_00000"},{"time":0.0333,"name":"heilongpugong/zidan/huoqiu_00001"},{"time":0.0667,"name":"heilongpugong/zidan/huoqiu_00002"},{"time":0.1,"name":"heilongpugong/zidan/huoqiu_00003"},{"time":0.1333,"name":"heilongpugong/zidan/huoqiu_00004"},{"time":0.1667,"name":"heilongpugong/zidan/huoqiu_00005"},{"time":0.2,"name":"heilongpugong/zidan/huoqiu_00006"},{"time":0.2333,"name":"heilongpugong/zidan/huoqiu_00007"},{"time":0.2667,"name":"heilongpugong/zidan/huoqiu_00008"},{"time":0.3,"name":"heilongpugong/zidan/huoqiu_00009"},{"time":0.3333,"name":"heilongpugong/zidan/huoqiu_00010"},{"time":0.3667,"name":"heilongpugong/zidan/huoqiu_00011"},{"time":0.4,"name":"heilongpugong/zidan/huoqiu_00012"},{"time":0.4333,"name":"heilongpugong/zidan/huoqiu_00013"},{"time":0.4667,"name":"heilongpugong/zidan/huoqiu_00014"},{"time":0.5,"name":"heilongpugong/zidan/huoqiu_00015"},{"time":0.5333,"name":"heilongpugong/zidan/huoqiu_00016"},{"time":0.5667,"name":"heilongpugong/zidan/huoqiu_00017"},{"time":0.6,"name":"heilongpugong/zidan/huoqiu_00018"},{"time":0.6333,"name":"heilongpugong/zidan/huoqiu_00019"},{"time":0.6667,"name":"heilongpugong/zidan/huoqiu_00020"},{"time":0.7,"name":"heilongpugong/zidan/huoqiu_00021"}]}}},"skillattack":{"slots":{"hit":{"attachment":[{"name":"heilongpugong/hit/shouji_00019"},{"time":0.0333,"name":"heilongpugong/hit/shouji_00020"},{"time":0.0667,"name":"heilongpugong/hit/shouji_00021"},{"time":0.1,"name":"heilongpugong/hit/shouji_00022"},{"time":0.1333,"name":"heilongpugong/hit/shouji_00023"},{"time":0.1667,"name":"heilongpugong/hit/shouji_00024"},{"time":0.2,"name":"heilongpugong/hit/shouji_00025"},{"time":0.2333,"name":"heilongpugong/hit/shouji_00026"},{"time":0.2667,"name":"heilongpugong/hit/shouji_00027"},{"time":0.3,"name":"heilongpugong/hit/shouji_00028"},{"time":0.3333,"name":"heilongpugong/hit/shouji_00029"},{"time":0.3667,"name":"heilongpugong/hit/shouji_00030"},{"time":0.4,"name":"heilongpugong/hit/shouji_00031"},{"time":0.4333,"name":"heilongpugong/hit/shouji_00032"},{"time":0.4667,"name":"heilongpugong/hit/shouji_00033"},{"time":0.5,"name":"heilongpugong/hit/shouji_00034"},{"time":0.5333,"name":null}]}}}}}