{"skeleton":{"hash":"99ug6J18ofZ68lcen4Sv/TcTgpY","spine":"3.8.99","images":"./images/","audio":"G:/20201010界面/spine动画源文件/人物动画/150+角色spine/spineaaa"},"bones":[{"name":"root"},{"name":"All","parent":"root"},{"name":"effect/ult-3/Dujian_0000s_0000_01","parent":"All","scaleX":2.7453,"scaleY":2.1655},{"name":"effect/ult-3/eff_guang","parent":"All","scaleX":2.1816,"scaleY":2.1816},{"name":"arrow3","parent":"All","x":-198.46,"y":-5.49}],"slots":[{"name":"arrow3","bone":"arrow3"},{"name":"effect/ult-3/Dujian","bone":"effect/ult-3/Dujian_0000s_0000_01","color":"ffffffd8"},{"name":"effect/ult-3/Dujian_add","bone":"effect/ult-3/Dujian_0000s_0000_01","color":"c4fb829c","blend":"additive"},{"name":"effect/ult-3/eff_guang2","bone":"effect/ult-3/eff_guang","color":"ffffff40"},{"name":"effect/ult-3/eff_guang_add","bone":"effect/ult-3/eff_guang","color":"ffffff6f","blend":"additive"}],"skins":[{"name":"default","attachments":{"arrow3":{"effect/ult-3/arrow2":{"width":209,"height":33}},"effect/ult-3/Dujian":{"effect/ult-3/Dujian_0000s_0001_02":{"x":-59.7,"width":147,"height":51},"effect/ult-3/Dujian_0000s_0002_03":{"x":-59.7,"width":147,"height":51},"effect/ult-3/Dujian_0000s_0003_04":{"x":-59.7,"width":147,"height":51},"effect/ult-3/Dujian_0000s_0004_05":{"x":-59.7,"width":147,"height":51},"effect/ult-3/Dujian_0000s_0005_06":{"x":-59.7,"width":147,"height":51},"effect/ult-3/Dujian_0000s_0000_01":{"x":-59.7,"width":147,"height":51}},"effect/ult-3/Dujian_add":{"effect/ult-3/Dujian_0000s_0001_02":{"x":-59.7,"width":147,"height":51},"effect/ult-3/Dujian_0000s_0002_03":{"x":-59.7,"width":147,"height":51},"effect/ult-3/Dujian_0000s_0003_04":{"x":-59.7,"width":147,"height":51},"effect/ult-3/Dujian_0000s_0004_05":{"x":-59.7,"width":147,"height":51},"effect/ult-3/Dujian_0000s_0005_06":{"x":-59.7,"width":147,"height":51},"effect/ult-3/Dujian_0000s_0000_01":{"x":-59.7,"width":147,"height":51}},"effect/ult-3/eff_guang2":{"effect/ult-3/eff_guang":{"width":74,"height":74}},"effect/ult-3/eff_guang_add":{"effect/ult-3/eff_guang":{"width":74,"height":74}}}}],"animations":{"general_tail":{"slots":{"arrow3":{"attachment":[{"name":"effect/ult-3/arrow2"}]},"effect/ult-3/Dujian":{"attachment":[{"name":"effect/ult-3/Dujian_0000s_0000_01"},{"time":0.0667,"name":"effect/ult-3/Dujian_0000s_0001_02"},{"time":0.1333,"name":"effect/ult-3/Dujian_0000s_0002_03"},{"time":0.2,"name":"effect/ult-3/Dujian_0000s_0003_04"},{"time":0.2667,"name":"effect/ult-3/Dujian_0000s_0004_05"},{"time":0.3333,"name":"effect/ult-3/Dujian_0000s_0005_06"},{"time":0.4,"name":"effect/ult-3/Dujian_0000s_0000_01"}]},"effect/ult-3/Dujian_add":{"attachment":[{"name":"effect/ult-3/Dujian_0000s_0000_01"},{"time":0.0667,"name":"effect/ult-3/Dujian_0000s_0001_02"},{"time":0.1333,"name":"effect/ult-3/Dujian_0000s_0002_03"},{"time":0.2,"name":"effect/ult-3/Dujian_0000s_0003_04"},{"time":0.2667,"name":"effect/ult-3/Dujian_0000s_0004_05"},{"time":0.3333,"name":"effect/ult-3/Dujian_0000s_0005_06"},{"time":0.4,"name":"effect/ult-3/Dujian_0000s_0000_01"}]},"effect/ult-3/eff_guang2":{"attachment":[{"name":"effect/ult-3/eff_guang"}]},"effect/ult-3/eff_guang_add":{"attachment":[{"name":"effect/ult-3/eff_guang"}]}},"bones":{"effect/ult-3/eff_guang":{"scale":[{"curve":0.25,"c3":0.75},{"time":0.2,"x":1.128,"y":1.128,"curve":0.25,"c3":0.75},{"time":0.4}]}}}}}